hysteron/__init__.py
hysteron/hysteron.py
hysteron-0.1.0.dist-info/AUTHORS.rst
hysteron-0.1.0.dist-info/LICENSE
hysteron-0.1.0.dist-info/METADATA
hysteron-0.1.0.dist-info/WHEEL
hysteron-0.1.0.dist-info/top_level.txt
hysteron-0.1.0.dist-info/RECORD
