Metadata-Version: 2.1
Name: hysteron
Version: 0.1.0
Summary: Event-based simulation of hysterons (hysteretic 2-state subsystems)
Home-page: https://github.com/nkeim/hysteron
Author: Nathan Keim
Author-email: keim@psu.edu
License: Apache Software License 2.0
Keywords: hysteron
Platform: UNKNOWN
Classifier: License :: OSI Approved :: Apache Software License
Classifier: Natural Language :: English
Classifier: Programming Language :: Python :: 3
Classifier: Programming Language :: Python :: 3.5
Classifier: Programming Language :: Python :: 3.6
Classifier: Programming Language :: Python :: 3.7
Classifier: Programming Language :: Python :: 3.8
Requires-Python: >=3.5
License-File: LICENSE
License-File: AUTHORS.rst
Requires-Dist: numba (>=0.51)
